jsoncanon/__init__.py
jsoncanon/core.py
jsoncanon/functions.py
jsoncanon/py.typed
jsoncanon/util.py
jsoncanon-0.2.3.dist-info/LICENSE
jsoncanon-0.2.3.dist-info/METADATA
jsoncanon-0.2.3.dist-info/WHEEL
jsoncanon-0.2.3.dist-info/RECORD
