Metadata-Version: 2.1
Name: jsoncanon
Version: 0.2.3
Summary: Typed Python implementation of JSON Canonicalization Scheme as described in RFC 8785. Currently lacks full floating point support
Home-page: https://github.com/sveinugu/jsoncanon
License: Apache-2.0
Keywords: JSON,RFC-8785,canonicalization,deterministic,serialization,hash
Author: Sveinung Gundersen
Author-email: sveinugu@gmail.com
Requires-Python: >=3.8,<4.0
Classifier: Development Status :: 2 - Pre-Alpha
Classifier: Intended Audience :: Developers
Classifier: License :: OSI Approved :: Apache Software License
Classifier: Programming Language :: Python :: 3
Classifier: Programming Language :: Python :: 3.8
Classifier: Programming Language :: Python :: 3.9
Classifier: Programming Language :: Python :: 3.10
Classifier: Programming Language :: Python :: 3.11
Classifier: Programming Language :: Python :: 3.12
Classifier: Topic :: Software Development :: Libraries
Project-URL: Repository, https://github.com/sveinugu/jsoncanon
